[
  {
    "id": "a89df1c5-dfc0-464d-b9c6-37185bc73bd7",
    "title": "Land check with Himalayan view near Ranikhet",
    "price": "₹5,00,00,000",
    "location": "Basot, Ranikhet & Corbett",
    "description": "A breathtaking Himalayan view with an internal road developed across 100 Nali, situated just below the main road. Above the road lies the cherry-on-the-cake—an exceptional piece of land. If needed, the land check can be increased from 100 Nali to 300 Nali within 3 months",
    "features": [
      "Himalayan views",
      "Flat land",
      "Road access"
    ],
    "specs": {
      "bedrooms": "",
      "bathrooms": "",
      "area": "",
      "landSize": "216000 sq ft",
      "plotSize": "216000 sq ft",
      "plotDimensions": "216000 sq ft",
      "hasBedrooms": false,
      "hasBathrooms": false,
      "plotType": "mixed-use",
      "naliSize": "100"
    },
    "amenities": [
      "Water",
      "Electricity",
      "Sunlight"
    ],
    "images": [
      "/uploads/a89df1c5-dfc0-464d-b9c6-37185bc73bd7/image-0-1744294000078.jpg?t=1744294000079"
    ],
    "category": "buy",
    "propertyType": "plot",
    "createdAt": "2023-09-15T10:30:00.000Z",
    "updatedAt": "2025-04-18T11:56:39.132Z",
    "tourUrl": "https://www.youtube.com/embed/dQw4w9WgXcQ",
    "videoUrl": "/uploads/a89df1c5-dfc0-464d-b9c6-37185bc73bd7/video-0-1744694281493-1744694281494-1494-vid-20250409-wa0000.mp4?t=1744694281494&t=1744694281493",
    "featured": true,
    "featuredOrder": 4,
    "videoUrls": [
      "/uploads/a89df1c5-dfc0-464d-b9c6-37185bc73bd7/video-0-1744694281493-1744694281494-1494-vid-20250409-wa0000.mp4?t=1744694281494&t=1744694281493",
      "/uploads/a89df1c5-dfc0-464d-b9c6-37185bc73bd7/video-0-1744977097225-1744977097226-7226-whatsapp-video-2025-04-18-at-17.20.36.mp4?t=1744977097226&t=1744977097225"
    ]
  },
  {
    "id": "b97e2fc6-ea51-475b-bc6d-48193fc76bfa",
    "title": "Fully Furnished, Operational Resort for Sale in Jim Corbett",
    "price": "₹ 28,00,00,000",
    "location": "Choi, Ramnagar",
    "description": "A rare opportunity to own a beautifully furnished, fully operational resort in the heart of Jim Corbett. Ideal for nature lovers, investors, or hospitality professionals seeking a turn-key business in one of India’s top eco-tourism destinations.",
    "features": [
      "Parking – 30 – 40 vehicles",
      "2 Lifts with 4 Stair cases",
      "Lawn Area – 15000 Sq Ft. with separate pathways and Garden area",
      "Banquet – 3700 Sq Ft. (High Ceiling) Connected along with the Lawn (Separate from Lawn area)",
      "Restaurant – 120 Seats with Centralised AC Plant (Daikin)",
      "Swimming Pool with Deck & Changing Room",
      "Recreation Hall Connected with Swimming Pool",
      "Reception with GM Office",
      " 40 Feet Private Road Shared with 3 other Adjoining Resort Properties.",
      "Sewerage treatment plant",
      "Under Ground Water Storage 150000 Lts",
      "Under Ground Water Storage 150000 Lts",
      "Over Head Storage 28000 Lts",
      "Water Source – Under Ground Boring",
      "Pannel Room With Electric Pannel , Servo , VCB & Private Transformer",
      "Power Backup Of 200 KVA Genset",
      "Separate Invertors for all blocks",
      " MAP Passed with Set Back & Permissions",
      "All Approvals Obtained From All Govt. Authorities",
      "Rooms are equipped with 1.5 ton Daikin Split AC, Godrej Fridge, 50” Samsung Hospitality TV, Ozone Lockers & Ozone RFID card Locks",
      " All Furniture Made from 1st quality Plywood (Manilam) & Sagwaan Wood Chairs",
      "All UPVC Windows Made from CORA profiles"
    ],
    "specs": {
      "bedrooms": "50",
      "bathrooms": "55",
      "area": "45000 Sq Ft",
      "landSize": "",
      "plotSize": "",
      "plotDimensions": "",
      "hasBedrooms": true,
      "hasBathrooms": true,
      "naliSize": "20.83"
    },
    "amenities": [],
    "images": [
      "/uploads/b97e2fc6-ea51-475b-bc6d-48193fc76bfa/image-0-1744975680088-0088-whatsapp-image-2025-04-13-at-13.30.26.jpeg?t=1744975680088",
      "/uploads/b97e2fc6-ea51-475b-bc6d-48193fc76bfa/image-0-1744532201385.jpeg?t=1744532201386",
      "/uploads/b97e2fc6-ea51-475b-bc6d-48193fc76bfa/image-0-1744532186314.jpeg?t=1744532186315",
      "/uploads/b97e2fc6-ea51-475b-bc6d-48193fc76bfa/image-0-1744975442465-2465-whatsapp-image-2025-04-18-at-16.46.28.jpeg?t=1744975442465",
      "/uploads/b97e2fc6-ea51-475b-bc6d-48193fc76bfa/image-0-1744976606587-6587-whatsapp-image-2025-04-18-at-16.47.46.jpeg?t=1744976606587"
    ],
    "category": "buy",
    "propertyType": "resort",
    "createdAt": "2023-10-05T15:20:00.000Z",
    "updatedAt": "2025-04-18T11:43:26.590Z",
    "hasVideo": "true",
    "videoUrl": "/uploads/b97e2fc6-ea51-475b-bc6d-48193fc76bfa/video-1744613313433-1744613313433.mp4?t=1744613313433&t=1744613313433",
    "tourUrl": "",
    "featured": true,
    "featuredOrder": 5,
    "videoUrls": [
      "/uploads/b97e2fc6-ea51-475b-bc6d-48193fc76bfa/video-1744613313433-1744613313433.mp4?t=1744613313433&t=1744613313433"
    ]
  },
  {
    "id": "c15e3ad7-fb62-486c-9de8-52074fc88cde",
    "title": "Plot in Chakluva near Haldwani",
    "price": "₹ 15,40,00,00",
    "location": "Chakluva, Ramnagar",
    "description": "Spacious bungalow with breathtaking views of the Kumaon valleys. Featuring premium finishes and ample outdoor space for recreation.",
    "features": [
      "Valley views",
      "Landscaped garden",
      "Sun deck",
      "Modern kitchen",
      "Home office space"
    ],
    "specs": {
      "bedrooms": "",
      "bathrooms": "",
      "area": "",
      "landSize": "11000 sq ft",
      "plotSize": "11000 sq ft",
      "plotDimensions": "11000 sq ft",
      "hasBedrooms": false,
      "hasBathrooms": false,
      "plotType": "mixed-use",
      "naliSize": "5.10"
    },
    "amenities": [
      "Parking",
      "Security",
      "Garden",
      "Balcony",
      "BBQ area",
      "Wifi"
    ],
    "images": [
      "/uploads/c15e3ad7-fb62-486c-9de8-52074fc88cde/image-0-1744976952274-2274-screenshot-2025-04-18-at-5.18.52-pm.png?t=1744976952274"
    ],
    "category": "buy",
    "propertyType": "plot",
    "createdAt": "2023-11-20T09:45:00.000Z",
    "updatedAt": "2025-04-18T11:57:47.477Z",
    "videoUrls": [
      "/uploads/c15e3ad7-fb62-486c-9de8-52074fc88cde/video-0-1744976746451-1744976746451-6451-whatsapp-video-2025-04-18-at-17.15.21.mp4?t=1744976746451&t=1744976746451"
    ],
    "hasVideos": "true",
    "videoCount": "2",
    "videoUrl": "/uploads/c15e3ad7-fb62-486c-9de8-52074fc88cde/video-0-1744976746451-1744976746451-6451-whatsapp-video-2025-04-18-at-17.15.21.mp4?t=1744976746451&t=1744976746451",
    "tourUrl": "",
    "featured": true,
    "featuredOrder": 3
  },
  {
    "id": "01063753-c126-48c1-a86d-31831142e4f0",
    "title": "3 BHK Flats in Ranidhara",
    "price": "₹ 85,00,000",
    "location": "Ranidhara, Uttrakhand",
    "description": "Nestled amidst the tranquil landscapes of the Kumaon hills, this spacious 3-BHK flat in Ranidhara, Almora offers the perfect blend of modern comfort and natural beauty. With sunlit rooms, mountain views, and fresh pine-scented air, the flat is ideal for a peaceful lifestyle.",
    "features": [],
    "specs": {
      "bedrooms": "3",
      "bathrooms": "3",
      "area": "2000 sq ft",
      "landSize": "2000 sq ft",
      "plotSize": "",
      "plotDimensions": "",
      "hasBedrooms": true,
      "hasBathrooms": true
    },
    "amenities": [
      "Lift"
    ],
    "images": [
      "/uploads/01063753-c126-48c1-a86d-31831142e4f0/image-0-1744604971098.jpeg?t=1744604971098"
    ],
    "category": "buy",
    "propertyType": "flats",
    "createdAt": "2025-04-13T17:21:31.979Z",
    "updatedAt": "2025-04-18T12:04:24.895Z",
    "videoUrls": [
      "/uploads/01063753-c126-48c1-a86d-31831142e4f0/video-0-1744630751408-1744630751408-1408-ranidhara-3bhk.mp4?t=1744630751408&t=1744630751408",
      "/uploads/01063753-c126-48c1-a86d-31831142e4f0/video-0-1744977864793-1744977864793-4793-rani.mp4?t=1744977864793&t=1744977864793"
    ],
    "hasVideos": "true",
    "videoCount": "1",
    "tourUrl": "",
    "videoUrl": "/uploads/01063753-c126-48c1-a86d-31831142e4f0/video-0-1744630751408-1744630751408-1408-ranidhara-3bhk.mp4?t=1744630751408&t=1744630751408",
    "featured": true,
    "featuredOrder": 6
  },
  {
    "id": "fa6e954b-abfa-4745-a0f5-3e4fa7775b87",
    "title": "Prime Land Plot in Sundarpur Near Binsar Wildlife Sanctuary",
    "price": "30000000",
    "location": "Sundarpur, Binsar Wildlife Sanctuary ",
    "description": "Discover an exceptional opportunity to own a picturesque land plot in the serene locale of Sundarpur, just a stone’s throw from the renowned Binsar Wildlife Sanctuary. This plot offers breathtaking natural surroundings and endless potential for development—be it a future resort, a tranquil retreat, or a bespoke residential project",
    "features": [
      "Breathtaking Himalayan Panorama",
      "Proximity to Binsar Wildlife Sanctuary",
      "Road Connectivity & Accessibility",
      "Tranquil Hilltop Setting",
      "Ample Space & Natural Terrain",
      "Eco-Friendly Living",
      "Strong Investment Value"
    ],
    "specs": {
      "bedrooms": "0",
      "bathrooms": "0",
      "area": "0 sq ft",
      "landSize": "37125 sqft",
      "plotSize": "37125 sqft",
      "plotDimensions": "37125 sqft",
      "hasBedrooms": true,
      "hasBathrooms": true,
      "plotType": "mixed-use",
      "naliSize": "17.2"
    },
    "amenities": [],
    "images": [
      "/uploads/fa6e954b-abfa-4745-a0f5-3e4fa7775b87/image-0-1744649741957-1957-sundarpur.png?t=1744649741957"
    ],
    "category": "buy",
    "propertyType": "plot",
    "createdAt": "2025-04-14T16:55:41.955Z",
    "updatedAt": "2025-04-18T11:57:11.277Z",
    "featured": true,
    "featuredOrder": 5,
    "videoUrls": [
      "/uploads/fa6e954b-abfa-4745-a0f5-3e4fa7775b87/video-0-1744977298483-1744977298484-8484-whatsapp-video-2025-04-14-at-21.08.38.mp4?t=1744977298484&t=1744977298483"
    ],
    "videoUrl": "/uploads/fa6e954b-abfa-4745-a0f5-3e4fa7775b87/video-0-1744977298483-1744977298484-8484-whatsapp-video-2025-04-14-at-21.08.38.mp4?t=1744977298484&t=1744977298483",
    "tourUrl": ""
  },
  {
    "id": "c278cf92-3adf-43ce-ba23-6c171561c26e",
    "title": "Scenic Roadside Land in Shitlakhet",
    "price": "1,80,00000",
    "location": "Shitlakhet, Almora",
    "description": "Whether you envision a peaceful hillside residence or a hospitality venture tapping into the area’s tourism, this land in Shitlakhet offers the rare blend of scenic beauty and strategic location. Property Size: 6.5 Naali (Registered) & 4 Naali (Unregistered)\n\n",
    "features": [
      "Prime Roadside Location",
      "Panoramic Himalaya Views",
      "Serene & Pleasant Climate",
      "Eco-Friendly Opportunities",
      "Investment Value"
    ],
    "specs": {
      "bedrooms": "0",
      "bathrooms": "0",
      "area": "0 sq ft",
      "landSize": "22,680 sq ft",
      "plotSize": "22,680 sq ft",
      "plotDimensions": "22,680 sq ft",
      "hasBedrooms": true,
      "hasBathrooms": true,
      "plotType": "mixed-use",
      "naliSize": "10.5"
    },
    "amenities": [],
    "images": [
      "/uploads/c278cf92-3adf-43ce-ba23-6c171561c26e/image-0-1744650402708-2708-whatsapp-image-2025-04-13-at-14.03.59-1-.jpeg?t=1744650402708"
    ],
    "category": "buy",
    "propertyType": "plot",
    "createdAt": "2025-04-14T17:06:42.706Z",
    "updatedAt": "2025-04-18T12:05:53.842Z",
    "featured": true,
    "featuredOrder": 6,
    "videoUrls": [
      "/uploads/c278cf92-3adf-43ce-ba23-6c171561c26e/video-0-1744651091833-1744651091833-1833-whatsapp-video-2025-04-13-at-14.04.37.mp4?t=1744651091833&t=1744651091833"
    ],
    "videoUrl": "/uploads/c278cf92-3adf-43ce-ba23-6c171561c26e/video-0-1744651091833-1744651091833-1833-whatsapp-video-2025-04-13-at-14.04.37.mp4?t=1744651091833&t=1744651091833",
    "tourUrl": ""
  },
  {
    "id": "880ddfcd-38a9-4f18-ae9e-41c413ea4147",
    "title": "2000 nali ",
    "price": "150000000",
    "location": "Champawat, Pithoragarh",
    "description": "2000 nali ",
    "features": [
      "River View",
      "360 Degree View",
      "Eco‑Friendly & Sustainable Projects",
      "Strong Long‑Term Appreciation",
      "Pristine Environment & Healthy Climate"
    ],
    "specs": {
      "bedrooms": "0",
      "bathrooms": "0",
      "area": "0 sq ft",
      "landSize": "4320000 sq ft",
      "plotSize": "",
      "plotDimensions": "",
      "hasBedrooms": true,
      "hasBathrooms": true,
      "naliSize": "2000"
    },
    "amenities": [],
    "images": [
      "/uploads/880ddfcd-38a9-4f18-ae9e-41c413ea4147/image-0-1744978514071-4071-whatsapp-image-2025-04-18-at-17.37.19-1-.jpeg?t=1744978514071"
    ],
    "category": "buy",
    "propertyType": "plot",
    "createdAt": "2025-04-18T12:15:14.070Z",
    "updatedAt": "2025-04-18T12:25:49.744Z",
    "featured": true,
    "featuredOrder": 7,
    "videoUrls": [
      "/uploads/880ddfcd-38a9-4f18-ae9e-41c413ea4147/video-0-1744978650864-1744978650864-0864-whatsapp-video-2025-04-18-at-17.38.44.mp4?t=1744978650864&t=1744978650864"
    ],
    "videoUrl": "/uploads/880ddfcd-38a9-4f18-ae9e-41c413ea4147/video-0-1744978650864-1744978650864-0864-whatsapp-video-2025-04-18-at-17.38.44.mp4?t=1744978650864&t=1744978650864",
    "tourUrl": ""
  },
  {
    "id": "0117ad99-e1df-4c42-bdd9-b94d72a3ec8c",
    "title": "Beautiful Land Plot in Sundarpur",
    "price": "4200000",
    "location": "Sundarpur Near Binsar Wildlife Sanctuary",
    "description": "1 nal 11 muthhi",
    "features": [],
    "specs": {
      "bedrooms": "0",
      "bathrooms": "0",
      "area": "0 sq ft",
      "landSize": "3645 sq ft",
      "plotSize": "",
      "plotDimensions": "",
      "hasBedrooms": true,
      "hasBathrooms": true,
      "naliSize": "1.11"
    },
    "amenities": [],
    "images": [
      "/uploads/0117ad99-e1df-4c42-bdd9-b94d72a3ec8c/image-0-1744979083747-3747-whatsapp-image-2025-04-18-at-17.54.19.jpeg?t=1744979083747"
    ],
    "category": "buy",
    "propertyType": "plot",
    "createdAt": "2025-04-18T12:24:43.746Z",
    "updatedAt": "2025-04-18T12:26:09.721Z",
    "featured": true,
    "featuredOrder": 8,
    "videoUrls": [],
    "videoUrl": "",
    "tourUrl": ""
  },
  {
    "id": "3cf7f08a-7661-4c35-8352-c0b45ff726d2",
    "title": "Beautiful 5 nali himalayan facing",
    "price": "8000000",
    "location": "Sundarpur Near Binsar Wildlife Sanctuary",
    "description": "5 nali",
    "features": [],
    "specs": {
      "bedrooms": "0",
      "bathrooms": "0",
      "area": "0 sq ft",
      "landSize": "10800 sq ft"
    },
    "amenities": [],
    "images": [
      "/uploads/3cf7f08a-7661-4c35-8352-c0b45ff726d2/image-0-1744979332130-2130-whatsapp-image-2025-04-18-at-17.56.14.jpeg?t=1744979332130"
    ],
    "category": "buy",
    "propertyType": "plot",
    "createdAt": "2025-04-18T12:28:52.129Z",
    "updatedAt": "2025-04-18T12:28:52.129Z",
    "featured": true,
    "featuredOrder": 9,
    "videoUrls": []
  }
]